pib/__init__.py
pib/__main__.py
pib/build.py
pib/cli.py
pib/exceptions.py
pib/git.py
pib/makefile.py
pib/module.py
pib/spec.py
pib/util.py
pib/git_template/hooks/post-checkout
pib/tests/__init__.py
pib/tests/conftest.py
pib/tests/test_blank.py
pib-0.0.1.dist-info/AUTHORS.rst
pib-0.0.1.dist-info/LICENSE
pib-0.0.1.dist-info/METADATA
pib-0.0.1.dist-info/WHEEL
pib-0.0.1.dist-info/entry_points.txt
pib-0.0.1.dist-info/top_level.txt
pib-0.0.1.dist-info/RECORD
