Metadata-Version: 2.1
Name: pib
Version: 0.0.1
Summary: IOC building tools
Author: SLAC National Accelerator Laboratory
License: Copyright (c) 2023, The Board of Trustees of the Leland Stanford Junior
Classifier: Development Status :: 2 - Pre-Alpha
Classifier: Natural Language :: English
Classifier: Programming Language :: Python :: 3
Requires-Python: >=3.9
License-File: LICENSE
License-File: AUTHORS.rst
Requires-Dist: apischema (==0.18.0)
Requires-Dist: click (==8.1.3)
Requires-Dist: pyyaml (==6.0)
Requires-Dist: whatrecord (==0.4.2)
Requires-Dist: typing-extensions
Provides-Extra: test
Requires-Dist: pytest ; extra == 'test'
